chaps_nats/__init__.py
chaps_nats/nats_context.py
chaps_nats/nats_job.py
chaps_nats/api/__init__.py
chaps_nats/api/jobs_api.py
chaps_nats/workers/__init__.py
chaps_nats/workers/worker.py
chaps_nats-0.0.4.dist-info/LICENSE
chaps_nats-0.0.4.dist-info/METADATA
chaps_nats-0.0.4.dist-info/WHEEL
chaps_nats-0.0.4.dist-info/top_level.txt
chaps_nats-0.0.4.dist-info/RECORD
