Metadata-Version: 2.1
Name: chaps_nats
Version: 0.0.4
Summary: Tools to design Job APIs on top of NATS
Author-email: Pierre Dellenbach <pdellenbach@chapsvision.com>
Classifier: Programming Language :: Python :: 3
Classifier: License :: OSI Approved :: Apache Software License
Classifier: Operating System :: OS Independent
Requires-Python: >=3.8
License-File: LICENSE
Requires-Dist: nats-py ~=2.6.0
Requires-Dist: fastapi[all] ~=0.111.0
Requires-Dist: asyncio ~=3.4.3
Requires-Dist: rich ~=13.7.1
Requires-Dist: json-tricks ~=3.17.3
